enigma/__init__.py
enigma/endpoints.py
enigma/models.py
enigma/tableview.py
enigma/util.py
enigma/swagger_client/__init__.py
enigma/swagger_client/api_client.py
enigma/swagger_client/configuration.py
enigma/swagger_client/rest.py
enigma/swagger_client/api/__init__.py
enigma/swagger_client/api/collection_api.py
enigma/swagger_client/api/dataset_api.py
enigma/swagger_client/api/dataset_summary_api.py
enigma/swagger_client/api/default_api.py
enigma/swagger_client/api/personal_collection_api.py
enigma/swagger_client/api/policy_api.py
enigma/swagger_client/api/snapshot_api.py
enigma/swagger_client/api/tags_api.py
enigma/swagger_client/api/user_api.py
enigma/swagger_client/models/__init__.py
enigma/swagger_client/models/apicollections_parent_collection.py
enigma/swagger_client/models/apicollections_tags.py
enigma/swagger_client/models/apidatasets_dependencies.py
enigma/swagger_client/models/apidatasets_source_lag_time.py
enigma/swagger_client/models/apidatasetsdataset_idsnapshotssnapshot_id_fields.py
enigma/swagger_client/models/apipersonalcollections_bookmarks.py
enigma/swagger_client/models/apipersonalcollections_collection.py
enigma/swagger_client/models/apipolicies_clause.py
enigma/swagger_client/models/apiusers_profile.py
enigma/swagger_client/models/apiusers_roles.py
enigma/swagger_client/models/body.py
enigma/swagger_client/models/body_1.py
enigma/swagger_client/models/body_10.py
enigma/swagger_client/models/body_11.py
enigma/swagger_client/models/body_12.py
enigma/swagger_client/models/body_13.py
enigma/swagger_client/models/body_2.py
enigma/swagger_client/models/body_3.py
enigma/swagger_client/models/body_4.py
enigma/swagger_client/models/body_5.py
enigma/swagger_client/models/body_6.py
enigma/swagger_client/models/body_7.py
enigma/swagger_client/models/body_8.py
enigma/swagger_client/models/body_9.py
enigma/swagger_client/models/collection.py
enigma/swagger_client/models/collection_ancestors.py
enigma_sdk-1.0.4.dist-info/DESCRIPTION.rst
enigma_sdk-1.0.4.dist-info/METADATA
enigma_sdk-1.0.4.dist-info/RECORD
enigma_sdk-1.0.4.dist-info/WHEEL
enigma_sdk-1.0.4.dist-info/metadata.json
enigma_sdk-1.0.4.dist-info/top_level.txt
