Metadata-Version: 2.0
Name: enigma-sdk
Version: 1.0.4
Summary: Enigma Public SDK
Home-page: https://public.enigma.com/
Author: Enigma
Author-email: public-support@enigma.com
License: UNKNOWN
Project-URL: Documentation, http://docs.enigma.com/public/public_v20_sdk_about.html
Keywords: enigma public data api sdk
Platform: UNKNOWN
Classifier: Development Status :: 5 - Production/Stable
Classifier: Intended Audience :: Developers
Classifier: License :: OSI Approved :: MIT License
Classifier: Natural Language :: English
Classifier: Operating System :: OS Independent
Classifier: Programming Language :: Python
Classifier: Programming Language :: Python :: 3
Classifier: Programming Language :: Python :: 3.4
Classifier: Programming Language :: Python :: 3.5
Classifier: Programming Language :: Python :: 3.6
Classifier: Programming Language :: Python :: 3.7
Classifier: Topic :: Software Development :: Libraries :: Python Modules
Requires-Python: ~=3.4
Requires-Dist: urllib3 (>=1.15)
Requires-Dist: six (>=1.10)
Requires-Dist: certifi
Requires-Dist: python-dateutil
